epc_api/__init__.py
epc_api/client.py
epc_api/exceptions.py
epc_api/schemas.py
epc_api_python-1.0.2.dist-info/LICENSE
epc_api_python-1.0.2.dist-info/METADATA
epc_api_python-1.0.2.dist-info/WHEEL
epc_api_python-1.0.2.dist-info/top_level.txt
epc_api_python-1.0.2.dist-info/RECORD
