Metadata-Version: 2.1
Name: epc-api-python
Version: 1.0.2
Summary: Interface the UK Govenment EPC api
Author: Khalim Conn-Kowlessar
License: Copyright (c) 2023 Khalim Conn-Kowlessar
Project-URL: Homepage, https://github.com/KhalimCK/epc-api-python
Keywords: epc_api
Classifier: License :: OSI Approved :: MIT License
Classifier: Programming Language :: Python
Classifier: Programming Language :: Python :: 3
Requires-Python: >=3.7
License-File: LICENSE
Requires-Dist: nose
Requires-Dist: sphinx
Requires-Dist: pydantic (>=1.10.7)
Requires-Dist: requests (>=2.28.2)
Provides-Extra: dev
Requires-Dist: pytest (>=6.2.3) ; extra == 'dev'
Requires-Dist: pytest-cov (>=4.0.0) ; extra == 'dev'
Requires-Dist: black (>=19.10b0) ; extra == 'dev'
Requires-Dist: isort ; extra == 'dev'
Requires-Dist: prospector ; extra == 'dev'
